pysat/__init__.py
pysat/modules.py
pysat_abel-0.1.3.dist-info/licenses/LICENSE
pysat_abel-0.1.3.dist-info/METADATA
pysat_abel-0.1.3.dist-info/WHEEL
pysat_abel-0.1.3.dist-info/top_level.txt
pysat_abel-0.1.3.dist-info/RECORD
