Metadata-Version: 2.4
Name: pysat-abel
Version: 0.1.3
Summary: Python implementation for Spline-based Abel Transform
Home-page: https://gitlab.coria-cfd.fr/littinm/pysat
Author: Mijail Littin, Alexandre Poux, Guillaume Lefevre, Marek Mazur, Felipe Escudero, Andrés Fuentes, Jérôme Yon
Author-email: littinm@coria.fr
License: MIT
Classifier: Intended Audience :: Science/Research
License-File: LICENSE
Requires-Dist: scipy
Requires-Dist: numpy
Requires-Dist: abel
Requires-Dist: joblib
Dynamic: author
Dynamic: author-email
Dynamic: classifier
Dynamic: description
Dynamic: description-content-type
Dynamic: home-page
Dynamic: license
Dynamic: license-file
Dynamic: requires-dist
Dynamic: summary
